Workbook

Sheet Inventory
A1: THE KITCHEN TCG — INVENTORY (Source of Truth)
A2: Publish this tab as CSV and sync into the app. Includes avg purchase price for P&L reference.
A4: product_name | B4: set_name | C4: short_name | D4: item_type | E4: quantity | F4: sticker_price | G4: avg_purchase_price | H4: image_url | I4: tcgplayer_url | J4: alt_url | K4: cardladder_url
A5: Full product name | B5: Set / series | C5: Short name shown in app | D5: Sealed | Singles | Graded | E5: Units in stock | F5: Sell price (auto-loads to app) | G5: Avg cost from Purchase History tab | H5: Direct image URL | I5: TCGPlayer URL — Sealed & Singles | J5: Alt.xyz URL — Graded only | K5: Card Ladder URL — Graded only
A6: ★ Gold=all Blue=Sealed/Singles Amber=Graded Green=calculated from Purchase History (do not edit manually)
A7: 151 Pokemon Center Elite Trainer Box Case | B7: 151 | C7: 151 PC ETB Case | D7: Sealed | E7: 2 | F7: 2000 | G7: =IFERROR(AVERAGEIF('Purchase History'!B:B,C7,'Purchase History'!E:E),"") | H7: https://tcgplayer-cdn.tcgplayer.com/product/528030_in_1000x1000.jpg | I7: https://www.tcgplayer.com/product/528030/pokemon-sv-scarlet-and-violet-151-151-pokemon-center-elite-trainer-box-exclusive-case?Language=English&page=1
A8: Hidden Fates Elite Trainer Box Case | B8: Hidden Fates | C8: Hidden Fates ETB Case | D8: Sealed | E8: 2 | F8: 1990 | G8: =IFERROR(AVERAGEIF('Purchase History'!B:B,C8,'Purchase History'!E:E),"") | H8: https://tcgplayer-cdn.tcgplayer.com/product/648466_in_1000x1000.jpg | I8: https://www.tcgplayer.com/product/648466/pokemon-hidden-fates-hidden-fates-elite-trainer-box-case?Language=English&page=1
A9: 151 Elite Trainer Box Case | B9: 151 | C9: 151 ETB Case | D9: Sealed | E9: 2 | F9: 1980 | G9: =IFERROR(AVERAGEIF('Purchase History'!B:B,C9,'Purchase History'!E:E),"") | H9: https://tcgplayer-cdn.tcgplayer.com/product/506640_in_1000x1000.jpg | I9: https://www.tcgplayer.com/product/506640/pokemon-sv-scarlet-and-violet-151-151-elite-trainer-box-case?Language=English&page=1
A10: Evolving Skies Elite Trainer Box Case | B10: Evolving Skies | C10: Evolving Skies ETB Case | D10: Sealed | E10: 2 | F10: 1970 | G10: =IFERROR(AVERAGEIF('Purchase History'!B:B,C10,'Purchase History'!E:E),"") | H10: https://tcgplayer-cdn.tcgplayer.com/product/243722_in_1000x1000.jpg | I10: https://www.tcgplayer.com/product/243722/pokemon-swsh07-evolving-skies-evolving-skies-elite-trainer-box-case?Language=English&page=1
A11: Fusion Strike Elite Trainer Box Case | B11: Fusion Strike | C11: Fusion Strike ETB Case | D11: Sealed | E11: 2 | F11: 1960 | G11: =IFERROR(AVERAGEIF('Purchase History'!B:B,C11,'Purchase History'!E:E),"") | H11: https://tcgplayer-cdn.tcgplayer.com/product/256271_in_1000x1000.jpg | I11: https://www.tcgplayer.com/product/256271/pokemon-swsh08-fusion-strike-fusion-strike-elite-trainer-box-case?Language=English&page=1
A12: Paldean Fates Elite Trainer Box Case | B12: Paldean Fates | C12: Paldean Fates ETB Case | D12: Sealed | E12: 2 | F12: 1950 | G12: =IFERROR(AVERAGEIF('Purchase History'!B:B,C12,'Purchase History'!E:E),"") | H12: https://tcgplayer-cdn.tcgplayer.com/product/530700_in_1000x1000.jpg | I12: https://www.tcgplayer.com/product/530700/pokemon-sv-paldean-fates-paldean-fates-elite-trainer-box-case?Language=English&page=1
A13: Celebrations Elite Trainer Box Case | B13: Celebrations | C13: Celebrations ETB Case | D13: Sealed | E13: 2 | F13: 1940 | G13: =IFERROR(AVERAGEIF('Purchase History'!B:B,C13,'Purchase History'!E:E),"") | H13: https://tcgplayer-cdn.tcgplayer.com/product/251895_in_1000x1000.jpg | I13: https://www.tcgplayer.com/product/251895/pokemon-celebrations-celebrations-elite-trainer-box-case?Language=English&page=1
A14: Crown Zenith Elite Trainer Box Case | B14: Crown Zenith | C14: Crown Zenith ETB Case | D14: Sealed | E14: 2 | F14: 1930 | G14: =IFERROR(AVERAGEIF('Purchase History'!B:B,C14,'Purchase History'!E:E),"") | H14: https://tcgplayer-cdn.tcgplayer.com/product/453471_in_1000x1000.jpg | I14: https://www.tcgplayer.com/product/453471/pokemon-crown-zenith-crown-zenith-elite-trainer-box-case?Language=English&page=1
A15: Evolving Skies Booster Box | B15: Evolving Skies | C15: Evolving Skies Booster Box | D15: Sealed | E15: 2 | F15: 1920 | G15: =IFERROR(AVERAGEIF('Purchase History'!B:B,C15,'Purchase History'!E:E),"") | H15: https://tcgplayer-cdn.tcgplayer.com/product/242436_in_1000x1000.jpg | I15: https://www.tcgplayer.com/product/242436/pokemon-swsh07-evolving-skies-evolving-skies-booster-box?Language=English&page=1
A16: Prismatic Evolutions Pokemon Center Elite Trainer Box Case | B16: Prismatic Evolutions | C16: Prismatic Evolutions PC ETB Case | D16: Sealed | E16: 2 | F16: 1910 | G16: =IFERROR(AVERAGEIF('Purchase History'!B:B,C16,'Purchase History'!E:E),"") | H16: https://tcgplayer-cdn.tcgplayer.com/product/600697_in_1000x1000.jpg | I16: https://www.tcgplayer.com/product/600697/pokemon-sv-prismatic-evolutions-prismatic-evolutions-pokemon-center-elite-trainer-box-exclusive-case?Language=English&page=1
A17: Crown Zenith Pokemon Center Elite Trainer Box Plus Case | B17: Crown Zenith | C17: Crown Zenith PC ETB Plus Case | D17: Sealed | E17: 2 | F17: 1900 | G17: =IFERROR(AVERAGEIF('Purchase History'!B:B,C17,'Purchase History'!E:E),"") | H17: https://tcgplayer-cdn.tcgplayer.com/product/454247_in_1000x1000.jpg | I17: https://www.tcgplayer.com/product/454247/pokemon-crown-zenith-crown-zenith-pokemon-center-elite-trainer-box-plus-case?Language=English&page=1
A18: 151 Booster Bundle Display | B18: 151 | C18: 151 Booster Bundle Display | D18: Sealed | E18: 2 | F18: 1890 | G18: =IFERROR(AVERAGEIF('Purchase History'!B:B,C18,'Purchase History'!E:E),"") | H18: https://tcgplayer-cdn.tcgplayer.com/product/513405_in_1000x1000.jpg | I18: https://www.tcgplayer.com/product/513405/pokemon-sv-scarlet-and-violet-151-151-booster-bundle-display?Language=English&page=1
A19: Prismatic Evolutions Elite Trainer Box Case | B19: Prismatic Evolutions | C19: Prismatic Evolutions ETB Case | D19: Sealed | E19: 2 | F19: 1880 | G19: =IFERROR(AVERAGEIF('Purchase History'!B:B,C19,'Purchase History'!E:E),"") | H19: https://tcgplayer-cdn.tcgplayer.com/product/598487_in_1000x1000.jpg | I19: https://www.tcgplayer.com/product/598487/pokemon-sv-prismatic-evolutions-prismatic-evolutions-elite-trainer-box-case?Language=English&page=1
A20: Sword & Shield Charizard Ultra Premium Collection Case | B20: Lost Origin | C20: Sword & Shield Charizard UPC Case | D20: Sealed | E20: 2 | F20: 1870 | G20: =IFERROR(AVERAGEIF('Purchase History'!B:B,C20,'Purchase History'!E:E),"") | H20: https://tcgplayer-cdn.tcgplayer.com/product/454377_in_1000x1000.jpg | I20: https://www.tcgplayer.com/product/454377/pokemon-swsh11-lost-origin-sword-and-shield-ultra-premium-collection-charizard-case?Language=English&page=1
A21: Obsidian Flames Elite Trainer Box Case | B21: Obsidian Flames | C21: Obsidian Flames ETB Case | D21: Sealed | E21: 2 | F21: 1860 | G21: =IFERROR(AVERAGEIF('Purchase History'!B:B,C21,'Purchase History'!E:E),"") | H21: https://tcgplayer-cdn.tcgplayer.com/product/501265_in_1000x1000.jpg | I21: https://www.tcgplayer.com/product/501265/pokemon-sv03-obsidian-flames-obsidian-flames-elite-trainer-box-case?Language=English&page=1
A22: Paldea Evolved Elite Trainer Box Case | B22: Paldea Evolved | C22: Paldea Evolved ETB Case | D22: Sealed | E22: 2 | F22: 1850 | G22: =IFERROR(AVERAGEIF('Purchase History'!B:B,C22,'Purchase History'!E:E),"") | H22: https://tcgplayer-cdn.tcgplayer.com/product/496911_in_1000x1000.jpg | I22: https://www.tcgplayer.com/product/496911/pokemon-sv02-paldea-evolved-paldea-evolved-elite-trainer-box-case?Language=English&page=1
A23: Eevee Heroes Set Gym Box (JP) | B23: Eevee Heroes | C23: Eevee Heroes Set Gym Box (JP) | D23: Sealed | E23: 2 | F23: 1840 | G23: =IFERROR(AVERAGEIF('Purchase History'!B:B,C23,'Purchase History'!E:E),"") | H23: https://tcgplayer-cdn.tcgplayer.com/product/608794_in_1000x1000.jpg | I23: https://www.tcgplayer.com/product/608794/pokemon-japan-s6a-eevee-heroes-eevee-heroes-gym-box?Language=all&page=1
A24: Lost Origin Elite Trainer Box Case | B24: Lost Origin | C24: Lost Origin ETB Case | D24: Sealed | E24: 2 | F24: 1830 | G24: =IFERROR(AVERAGEIF('Purchase History'!B:B,C24,'Purchase History'!E:E),"") | H24: https://tcgplayer-cdn.tcgplayer.com/product/278796_in_1000x1000.jpg | I24: https://www.tcgplayer.com/product/278796/pokemon-swsh11-lost-origin-lost-origin-elite-trainer-box-case?Language=all&page=1
A25: Journey Together Enhanced Booster Box Case | B25: Journey Together | C25: Journey Together Enhanced Booster Box Case | D25: Sealed | E25: 2 | F25: 1820 | G25: =IFERROR(AVERAGEIF('Purchase History'!B:B,C25,'Purchase History'!E:E),"") | H25: https://tcgplayer-cdn.tcgplayer.com/product/625583_in_1000x1000.jpg | I25: https://www.tcgplayer.com/product/625583/pokemon-sv09-journey-together-journey-together-enhanced-booster-box-case?Language=all&page=1
A26: Cosmic Eclipse Elite Trainer Box | B26: Cosmic Eclipse | C26: Cosmic Eclipse ETB | D26: Sealed | E26: 2 | F26: 1810 | G26: =IFERROR(AVERAGEIF('Purchase History'!B:B,C26,'Purchase History'!E:E),"") | H26: https://tcgplayer-cdn.tcgplayer.com/product/199308_in_1000x1000.jpg | I26: https://www.tcgplayer.com/product/199308/pokemon-sm-cosmic-eclipse-cosmic-eclipse-elite-trainer-box?Language=English&page=1
A27: 151 Pokemon Center Elite Trainer Box | B27: 151 | C27: 151 PC ETB | D27: Sealed | E27: 2 | F27: 1800 | G27: =IFERROR(AVERAGEIF('Purchase History'!B:B,C27,'Purchase History'!E:E),"") | H27: https://tcgplayer-cdn.tcgplayer.com/product/501999_in_1000x1000.jpg | I27: https://www.tcgplayer.com/product/501999/pokemon-sv-scarlet-and-violet-151-151-pokemon-center-elite-trainer-box-exclusive?Language=all&page=1
A28: Ascended Heroes Elite Trainer Box Case | B28: Ascended Heroes | C28: Ascended Heroes ETB Case | D28: Sealed | E28: 2 | F28: 1790 | G28: =IFERROR(AVERAGEIF('Purchase History'!B:B,C28,'Purchase History'!E:E),"") | H28: https://tcgplayer-cdn.tcgplayer.com/product/668496_in_1000x1000.jpg | I28: https://www.tcgplayer.com/product/679558/pokemon-me-ascended-heroes-ascended-heroes-elite-trainer-box-case?Language=all&page=1
A29: Paradox Rift Elite Trainer Box Case | B29: Paradox Rift | C29: Paradox Rift ETB Case | D29: Sealed | E29: 2 | F29: 1780 | G29: =IFERROR(AVERAGEIF('Purchase History'!B:B,C29,'Purchase History'!E:E),"") | H29: https://tcgplayer-cdn.tcgplayer.com/product/512834_in_1000x1000.jpg | I29: https://www.tcgplayer.com/product/513511/pokemon-sv04-paradox-rift-paradox-rift-elite-trainer-box-case?Language=all&page=1
A30: Silver Tempest Elite Trainer Box Case | B30: Silver Tempest | C30: Silver Tempest ETB Case | D30: Sealed | E30: 2 | F30: 1770 | G30: =IFERROR(AVERAGEIF('Purchase History'!B:B,C30,'Purchase History'!E:E),"") | H30: https://tcgplayer-cdn.tcgplayer.com/product/285777_in_1000x1000.jpg | I30: https://www.tcgplayer.com/product/285777/pokemon-swsh12-silver-tempest-silver-tempest-elite-trainer-box-case?Language=all&page=1
A31: Brilliant Stars Elite Trainer Box Case | B31: Brilliant Stars | C31: Brilliant Stars ETB Case | D31: Sealed | E31: 2 | F31: 1760 | G31: =IFERROR(AVERAGEIF('Purchase History'!B:B,C31,'Purchase History'!E:E),"") | H31: https://tcgplayer-cdn.tcgplayer.com/product/264269_in_1000x1000.jpg | I31: https://www.tcgplayer.com/product/264269/pokemon-swsh09-brilliant-stars-brilliant-stars-elite-trainer-box-case?Language=all&page=1
A32: Hidden Fates Ultra Premium Collection | B32: Hidden Fates | C32: Hidden Fates UPC | D32: Sealed | E32: 2 | F32: 1750 | H32: https://tcgplayer-cdn.tcgplayer.com/product/199466_in_1000x1000.jpg | I32: https://www.tcgplayer.com/product/199466/pokemon-hidden-fates-hidden-fates-ultra-premium-collection?page=1&Language=all
A33: Black Bolt Elite Trainer Box Case | B33: Black Bolt | C33: Black Bolt ETB Case | D33: Sealed | E33: 2 | F33: 1740 | H33: https://tcgplayer-cdn.tcgplayer.com/product/630690_in_1000x1000.jpg | I33: https://www.tcgplayer.com/product/630690/pokemon-sv-black-bolt-black-bolt-elite-trainer-box-case?Language=all&page=1
A34: Lost Origin Pokemon Center Elite Trainer Box Case | B34: Lost Origin | C34: Lost Origin PC ETB Case | D34: Sealed | E34: 2 | F34: 1730 | H34: https://tcgplayer-cdn.tcgplayer.com/product/277336_in_1000x1000.jpg | I34: https://www.tcgplayer.com/product/652759/pokemon-swsh11-lost-origin-lost-origin-pokemon-center-elite-trainer-box-case-exclusive?Language=all&page=1
A35: White Flare Elite Trainer Box Case | B35: White Flare | C35: White Flare ETB Case | D35: Sealed | E35: 2 | F35: 1720 | H35: https://tcgplayer-cdn.tcgplayer.com/product/630693_in_1000x1000.jpg | I35: https://www.tcgplayer.com/product/630693/pokemon-sv-white-flare-white-flare-elite-trainer-box-case?Language=all&page=1
A36: Phantasmal Flames Elite Trainer Box Case | B36: Phantasmal Flames | C36: Phantasmal Flames ETB Case | D36: Sealed | E36: 2 | F36: 1710 | H36: https://tcgplayer-cdn.tcgplayer.com/product/654170_in_1000x1000.jpg | I36: https://www.tcgplayer.com/product/654170/pokemon-me02-phantasmal-flames-phantasmal-flames-elite-trainer-box-case?Language=all&page=1
A37: Shining Legends Elite Trainer Box | B37: Shining Legends | C37: Shining Legends ETB | D37: Sealed | E37: 2 | F37: 1700 | H37: https://tcgplayer-cdn.tcgplayer.com/product/145847_in_1000x1000.jpg | I37: https://www.tcgplayer.com/product/145847/pokemon-shining-legends-shining-legends-elite-trainer-box?Language=English&page=1
A38: 151 Ultra-Premium Collection | B38: 151 | C38: 151 UPC | D38: Sealed | E38: 2 | F38: 1690 | H38: https://tcgplayer-cdn.tcgplayer.com/product/502005_in_1000x1000.jpg | I38: https://www.tcgplayer.com/product/502005/pokemon-sv-scarlet-and-violet-151-151-ultra-premium-collection?Language=English&page=1
A39: Stellar Crown Elite Trainer Box Case | B39: Stellar Crown | C39: Stellar Crown ETB Case | D39: Sealed | E39: 2 | F39: 1680 | H39: https://tcgplayer-cdn.tcgplayer.com/product/559102_in_1000x1000.jpg | I39: https://www.tcgplayer.com/product/559102/pokemon-sv07-stellar-crown-stellar-crown-elite-trainer-box-case?Language=all&page=1
A40: Mega Evolution Elite Trainer Box Case | B40: Mega Evolution | C40: Mega Evolution ETB Case | D40: Sealed | E40: 2 | F40: 1670 | H40: https://tcgplayer-cdn.tcgplayer.com/product/648394_in_1000x1000.jpg | I40: https://www.tcgplayer.com/product/644727/pokemon-me01-mega-evolution-mega-evolution-elite-trainer-box-case?Language=all&page=1
A41: Stellar Crown Pokemon Center Elite Trainer Box Case | B41: Stellar Crown | C41: Stellar Crown PC ETB Case | D41: Sealed | E41: 2 | F41: 1660 | H41: https://tcgplayer-cdn.tcgplayer.com/product/557363_in_1000x1000.jpg | I41: https://www.tcgplayer.com/product/557363/pokemon-sv07-stellar-crown-stellar-crown-pokemon-center-elite-trainer-box-exclusive-case?Language=all&page=1
A42: Shrouded Fable Elite Trainer Box Case | B42: Shrouded Fable | C42: Shrouded Fable ETB Case | D42: Sealed | E42: 2 | F42: 1650 | H42: https://tcgplayer-cdn.tcgplayer.com/product/553099_in_1000x1000.jpg | I42: https://www.tcgplayer.com/product/553099/pokemon-sv-shrouded-fable-shrouded-fable-elite-trainer-box-case?Language=all&page=1
A43: Twilight Masquerade Elite Trainer Box Case | B43: Twilight Masquerade | C43: Twilight Masquerade ETB Case | D43: Sealed | E43: 2 | F43: 1640 | H43: https://tcgplayer-cdn.tcgplayer.com/product/544385_in_1000x1000.jpg | I43: https://www.tcgplayer.com/product/544385/pokemon-sv06-twilight-masquerade-twilight-masquerade-elite-trainer-box-case?Language=all&page=1
A44: Mega Charizard X ex Ultra Premium Collection Case | B44: Miscellaneous Cards & Products | C44: Mega Charizard X ex UPC Case | D44: Sealed | E44: 2 | F44: 1630 | H44: https://tcgplayer-cdn.tcgplayer.com/product/654213_in_1000x1000.jpg | I44: https://www.tcgplayer.com/product/664895/pokemon-miscellaneous-cards-and-products-mega-charizard-x-ex-ultra-premium-collection-case?Language=all&page=1
A45: Twilight Masquerade Pokemon Center Elite Trainer Box Case | B45: Twilight Masquerade | C45: Twilight Masquerade PC ETB Case | D45: Sealed | E45: 2 | F45: 1620 | H45: https://tcgplayer-cdn.tcgplayer.com/product/549491_in_1000x1000.jpg | I45: https://www.tcgplayer.com/product/549491/pokemon-sv06-twilight-masquerade-twilight-masquerade-pokemon-center-elite-trainer-box-exclusive-case?Language=all&page=1
A46: XY Evolutions Elite Trainer Box [Mega Charizard Y] | B46: Evolutions | C46: XY Evolutions ETB [Mega Charizard Y] | D46: Sealed | E46: 2 | F46: 1610 | H46: https://tcgplayer-cdn.tcgplayer.com/product/123447_in_1000x1000.jpg | I46: https://www.tcgplayer.com/product/123447/pokemon-xy-evolutions-xy-evolutions-elite-trainer-box-mega-charizard-y?Language=all&page=1
A47: 151 Elite Trainer Box | B47: 151 | C47: 151 ETB | D47: Sealed | E47: 2 | F47: 1600 | H47: https://tcgplayer-cdn.tcgplayer.com/product/503313_in_1000x1000.jpg | I47: https://www.tcgplayer.com/product/503313/pokemon-sv-scarlet-and-violet-151-151-elite-trainer-box?Language=all&page=1
A48: Prismatic Evolutions Pokemon Center Elite Trainer Box | B48: Prismatic Evolutions | C48: Prismatic Evolutions PC ETB | D48: Sealed | E48: 2 | F48: 1590 | H48: https://tcgplayer-cdn.tcgplayer.com/product/593324_in_1000x1000.jpg | I48: https://www.tcgplayer.com/product/593324/pokemon-sv-prismatic-evolutions-prismatic-evolutions-pokemon-center-elite-trainer-box-exclusive?Language=all&page=1
A49: XY Evolutions Elite Trainer Box [Mega Blastoise] | B49: Evolutions | C49: XY Evolutions ETB [Mega Blastoise] | D49: Sealed | E49: 2 | F49: 1580 | H49: https://tcgplayer-cdn.tcgplayer.com/product/123448_in_1000x1000.jpg | I49: https://www.tcgplayer.com/product/123448/pokemon-xy-evolutions-xy-evolutions-elite-trainer-box-mega-blastoise?Language=all&page=1
A50: Mythical Collection [Magearna] | B50: Evolutions | C50: Mythical Collection [Magearna] | D50: Sealed | E50: 2 | F50: 1570 | H50: https://tcgplayer-cdn.tcgplayer.com/product/127179_in_1000x1000.jpg | I50: https://www.tcgplayer.com/product/127179/pokemon-xy-evolutions-mythical-collection-magearna?Language=all&page=1
A51: Chilling Reign Booster Box | B51: Chilling Reign | C51: Chilling Reign Booster Box | D51: Sealed | E51: 2 | F51: 1560 | H51: https://tcgplayer-cdn.tcgplayer.com/product/236258_in_1000x1000.jpg | I51: https://www.tcgplayer.com/product/236258/pokemon-swsh06-chilling-reign-chilling-reign-booster-box?Language=all&page=1
A52: Sword & Shield Charizard Ultra Premium Collection | B52: Lost Origin | C52: Sword & Shield Charizard UPC | D52: Sealed | E52: 2 | F52: 1550 | H52: https://tcgplayer-cdn.tcgplayer.com/product/282401_in_1000x1000.jpg | I52: https://www.tcgplayer.com/product/282401/pokemon-swsh11-lost-origin-sword-and-shield-ultra-premium-collection-charizard?Language=English&page=1
A53: Celebrations Pokemon Center Elite Trainer Box | B53: Celebrations | C53: Celebrations PC ETB | D53: Sealed | E53: 2 | F53: 1540 | H53: https://tcgplayer-cdn.tcgplayer.com/product/251199_in_1000x1000.jpg | I53: https://www.tcgplayer.com/product/251199/pokemon-celebrations-celebrations-pokemon-center-elite-trainer-box-exclusive?Language=all&page=1
A54: Evolving Skies Elite Trainer Box [Flareon/Jolteon/Umbreon/Leafeon] | B54: Evolving Skies | C54: Evolving Skies ETB [Flareon/Jolteon/Umbreon/Leafeon] | D54: Sealed | E54: 2 | F54: 1530 | H54: https://tcgplayer-cdn.tcgplayer.com/product/242434_in_1000x1000.jpg | I54: https://www.tcgplayer.com/product/242434/pokemon-swsh07-evolving-skies-evolving-skies-elite-trainer-box-flareon-jolteon-umbreon-leafeon?Language=all&page=1
A55: Kanto Power Collection [Mewtwo EX/Slowbro EX] | B55: Evolutions | C55: Kanto Power Collection [Mewtwo EX/Slowbro EX] | D55: Sealed | E55: 2 | F55: 1520 | H55: https://tcgplayer-cdn.tcgplayer.com/product/222988_in_1000x1000.jpg | I55: https://www.tcgplayer.com/product/222988/pokemon-xy-evolutions-kanto-power-collection-mewtwo-ex-slowbro-ex?Language=all&page=1
A56: Destined Rivals Pokemon Center Elite Trainer Box | B56: Destined Rivals | C56: Destined Rivals PC ETB | D56: Sealed | E56: 2 | F56: 1510 | H56: https://tcgplayer-cdn.tcgplayer.com/product/624675_in_1000x1000.jpg | I56: https://www.tcgplayer.com/product/624675/pokemon-sv10-destined-rivals-destined-rivals-pokemon-center-elite-trainer-box-exclusive?Language=all&page=1
A57: Kanto Power Collection [Dragonite EX/Pidgeot EX] | B57: Evolutions | C57: Kanto Power Collection [Dragonite EX/Pidgeot EX] | D57: Sealed | E57: 2 | F57: 1500 | H57: https://tcgplayer-cdn.tcgplayer.com/product/222989_in_1000x1000.jpg | I57: https://www.tcgplayer.com/product/222989/pokemon-xy-evolutions-kanto-power-collection-dragonite-ex-pidgeot-ex?Language=all&page=1
A58: Hidden Fates Elite Trainer Box | B58: Hidden Fates | C58: Hidden Fates ETB | D58: Sealed | E58: 2 | F58: 1490 | H58: https://tcgplayer-cdn.tcgplayer.com/product/194729_in_1000x1000.jpg | I58: https://www.tcgplayer.com/product/194729/pokemon-hidden-fates-hidden-fates-elite-trainer-box?Language=all&page=1
A59: Precious Collector Box (JP) | B59: Miscellaneous Cards & Products | C59: Precious Collector Box (JP) | D59: Sealed | E59: 2 | F59: 1480 | H59: https://tcgplayer-cdn.tcgplayer.com/product/638934_in_1000x1000.jpg | I59: https://www.tcgplayer.com/product/638934/pokemon-japan-s-p-sword-and-shield-promos-sword-and-shield-precious-collector-box?Language=all&page=1
... A66: Celebrations Elite Trainer Box | B66: Celebrations | C66: Celebrations ETB | D66: Sealed | E66: 2 | F66: 1410 | H66: https://tcgplayer-cdn.tcgplayer.com/product/242811_in_1000x1000.jpg | I66: https://www.tcgplayer.com/product/242811/pokemon-celebrations-celebrations-elite-trainer-box?Language=all&page=1
A67: Blooming Waters Premium Collection | B67: 151 | C67: Blooming Waters Premium Collection | D67: Sealed | E67: 2 | F67: 1400 | H67: https://tcgplayer-cdn.tcgplayer.com/product/609597_in_1000x1000.jpg | I67: https://www.tcgplayer.com/product/609597/pokemon-miscellaneous-cards-and-products-blooming-waters-premium-collection?Language=all&page=1
A68: Flareon VMAX Premium Collection | B68: Miscellaneous Cards & Products | C68: Flareon VMAX Premium Collection | D68: Sealed | E68: 2 | F68: 1390 | H68: https://tcgplayer-cdn.tcgplayer.com/product/249705_in_1000x1000.jpg | I68: https://www.tcgplayer.com/product/249705/pokemon-miscellaneous-cards-and-products-flareon-vmax-premium-collection?Language=all&page=1
A69: Jolteon VMAX Premium Collection | B69: Miscellaneous Cards & Products | C69: Jolteon VMAX Premium Collection | D69: Sealed | E69: 2 | F69: 1380 | H69: https://tcgplayer-cdn.tcgplayer.com/product/249693_in_1000x1000.jpg | I69: https://www.tcgplayer.com/product/249693/pokemon-miscellaneous-cards-and-products-jolteon-vmax-premium-collection?Language=all&page=1
A70: Sea & Sky Premium Collection | B70: Crown Zenith | C70: Sea & Sky Premium Collection | D70: Sealed | E70: 2 | F70: 1370 | H70: https://tcgplayer-cdn.tcgplayer.com/product/563307_in_1000x1000.jpg | I70: https://www.tcgplayer.com/product/563307/pokemon-crown-zenith-sea-and-sky-premium-collection?Language=all&page=1
A71: Surging Sparks Booster Box | B71: Surging Sparks | C71: Surging Sparks Booster Box | D71: Sealed | E71: 2 | F71: 1360 | H71: https://tcgplayer-cdn.tcgplayer.com/product/565606_in_1000x1000.jpg | I71: https://www.tcgplayer.com/product/565606/pokemon-sv08-surging-sparks-surging-sparks-booster-box?Language=all&page=1
A72: Team Rocket’s Moltres ex Ultra-Premium Collection | B72: Destined Rivals | C72: Team Rocket’s Moltres ex UPC | D72: Sealed | E72: 2 | F72: 1350 | H72: https://tcgplayer-cdn.tcgplayer.com/product/656997_in_1000x1000.jpg | I72: https://www.tcgplayer.com/product/656997/pokemon-miscellaneous-cards-and-products-team-rockets-moltres-ex-ultra-premium-collection?Language=all&page=1
A73: Costco Pokemon Prismatic Evolutions 2-Pack Trainer Box and Booster Bundle | B73: Prismatic Evolutions | C73: Costco Pokemon Prismatic Evolutions 2-Pack Trainer Box and Booster Bundle | D73: Sealed | E73: 2 | F73: 1340 | H73: https://tcgplayer-cdn.tcgplayer.com/product/636740_in_1000x1000.jpg | I73: https://www.tcgplayer.com/product/636740/pokemon-miscellaneous-cards-and-products-costco-pokemon-prismatic-evolutions-2-pack-trainer-box-and-booster-bundle?Language=all&page=1
A74: Reshiram & Charizard GX Premium Collection | B74: Miscellaneous Cards & Products | C74: Reshiram & Charizard GX Premium Collection | D74: Sealed | E74: 2 | F74: 1330 | H74: https://tcgplayer-cdn.tcgplayer.com/product/248208_in_1000x1000.jpg | I74: https://www.tcgplayer.com/product/248208/pokemon-miscellaneous-cards-and-products-reshiram-and-charizard-gx-premium-collection?Language=all&page=1
A75: Phantasmal Flames Pokemon Center Elite Trainer Box | B75: Phantasmal Flames | C75: Phantasmal Flames PC ETB | D75: Sealed | E75: 2 | F75: 1320 | H75: https://tcgplayer-cdn.tcgplayer.com/product/654135_in_1000x1000.jpg | I75: https://www.tcgplayer.com/product/654135/pokemon-me02-phantasmal-flames-phantasmal-flames-pokemon-center-elite-trainer-box-exclusive?Language=all&page=1
A76: Black Bolt Pokemon Center Elite Trainer Box | B76: Black Bolt | C76: Black Bolt PC ETB | D76: Sealed | E76: 2 | F76: 1310 | H76: https://tcgplayer-cdn.tcgplayer.com/product/630687_in_1000x1000.jpg | I76: https://www.tcgplayer.com/product/630687/pokemon-sv-black-bolt-black-bolt-pokemon-center-elite-trainer-box-exclusive?Language=all&page=1
A77: Pikachu & Zekrom GX Premium Collection | B77: Miscellaneous Cards & Products | C77: Pikachu & Zekrom GX Premium Collection | D77: Sealed | E77: 2 | F77: 1300 | H77: https://tcgplayer-cdn.tcgplayer.com/product/253396_in_1000x1000.jpg | I77: https://www.tcgplayer.com/product/253396/pokemon-miscellaneous-cards-and-products-pikachu-and-zekrom-gx-premium-collection?Language=all&page=1
A78: Costco Prismatic Evolutions 8-Pack Mini Tins | B78: Prismatic Evolutions | C78: Costco Prismatic Evolutions 8-Pack Mini Tins | D78: Sealed | E78: 2 | F78: 1290 | H78: https://tcgplayer-cdn.tcgplayer.com/product/653892_in_1000x1000.jpg | I78: https://www.tcgplayer.com/product/653892/pokemon-miscellaneous-cards-and-products-costco-prismatic-evolutions-8-pack-mini-tins?Language=all&page=1
A79: Shining Legends: Shiny Zygarde GX Box | B79: Shining Legends | C79: Shining Legends: Shiny Zygarde GX Box | D79: Sealed | E79: 2 | F79: 1280 | H79: https://tcgplayer-cdn.tcgplayer.com/product/169543_in_1000x1000.jpg | I79: https://www.tcgplayer.com/product/169543/pokemon-shining-legends-shining-legends-shiny-zygarde-gx-box?Language=all&page=1
... A82: Destined Rivals Elite Trainer Box | B82: Destined Rivals | C82: Destined Rivals ETB | D82: Sealed | E82: 2 | F82: 1250 | H82: https://tcgplayer-cdn.tcgplayer.com/product/624676_in_1000x1000.jpg | I82: https://www.tcgplayer.com/product/624676/pokemon-sv10-destined-rivals-destined-rivals-elite-trainer-box?Language=all&page=1
A83: Costco Pokemon Scarlet & Violet 151 Mini Tin 5-pack (Magneton) | B83: 151 | C83: Costco Pokemon Scarlet & Violet 151 Mini Tin 5-pack (Magneton) | D83: Sealed | E83: 2 | F83: 1240 | H83: https://tcgplayer-cdn.tcgplayer.com/product/587747_in_1000x1000.jpg | I83: https://www.tcgplayer.com/product/587747/pokemon-miscellaneous-cards-and-products-costco-pokemon-scarlet-and-violet-151-mini-tin-5-pack-magneton?Language=all&page=1
A84: Brilliant Stars Pokemon Center Elite Trainer Box | B84: Brilliant Stars | C84: Brilliant Stars PC ETB | D84: Sealed | E84: 2 | F84: 1230 | H84: https://tcgplayer-cdn.tcgplayer.com/product/256140_in_1000x1000.jpg | I84: https://www.tcgplayer.com/product/256140/pokemon-swsh09-brilliant-stars-brilliant-stars-pokemon-center-elite-trainer-box-exclusive?Language=all&page=1
A85: Sun & Moon Elite Trainer Box [Lunala] | B85: Sun & Moon Base Set | C85: Sun & Moon ETB [Lunala] | D85: Sealed | E85: 2 | F85: 1220 | H85: https://tcgplayer-cdn.tcgplayer.com/product/126091_in_1000x1000.jpg | I85: https://www.tcgplayer.com/product/126091/pokemon-sm-base-set-sun-and-moon-elite-trainer-box-lunala?Language=all&page=1
A86: Prismatic Evolutions Elite Trainer Box | B86: Prismatic Evolutions | C86: Prismatic Evolutions ETB | D86: Sealed | E86: 2 | F86: 1210 | H86: https://tcgplayer-cdn.tcgplayer.com/product/593355_in_1000x1000.jpg | I86: https://www.tcgplayer.com/product/593355/pokemon-sv-prismatic-evolutions-prismatic-evolutions-elite-trainer-box?Language=all&page=1
A87: Pokemon Go Elite Trainer Box Plus | B87: Pokemon Go | C87: Pokemon Go ETB Plus | D87: Sealed | E87: 2 | F87: 1200 | H87: https://tcgplayer-cdn.tcgplayer.com/product/270709_in_1000x1000.jpg | I87: https://www.tcgplayer.com/product/270709/pokemon-pokemon-go-pokemon-go-pokemon-center-elite-trainer-box-plus-exclusive?Language=all&page=1
A88: Mega Charizard X ex Ultra Premium Collection | B88: Miscellaneous Cards & Products | C88: Mega Charizard X ex UPC | D88: Sealed | E88: 2 | F88: 1190 | H88: https://tcgplayer-cdn.tcgplayer.com/product/654213_in_1000x1000.jpg | I88: https://www.tcgplayer.com/product/654213/pokemon-miscellaneous-cards-and-products-mega-charizard-x-ex-ultra-premium-collection?Language=all&page=1
A89: White Flare Pokemon Center Elite Trainer Box | B89: White Flare | C89: White Flare PC ETB | D89: Sealed | E89: 2 | F89: 1180 | H89: https://tcgplayer-cdn.tcgplayer.com/product/630688_in_1000x1000.jpg | I89: https://www.tcgplayer.com/product/630688/pokemon-sv-white-flare-white-flare-pokemon-center-elite-trainer-box-exclusive?Language=all&page=1
A90: Prismatic Evolutions Premium Figure Collection | B90: Prismatic Evolutions | C90: Prismatic Evolutions Premium Figure Collection | D90: Sealed | E90: 2 | F90: 1170 | H90: https://tcgplayer-cdn.tcgplayer.com/product/650799_in_1000x1000.jpg | I90: https://www.tcgplayer.com/product/650799/pokemon-sv-prismatic-evolutions-prismatic-evolutions-premium-figure-collection?Language=all&page=1
A91: 151 Booster Bundle | B91: 151 | C91: 151 Booster Bundle | D91: Sealed | E91: 2 | F91: 1160 | H91: https://tcgplayer-cdn.tcgplayer.com/product/502000_in_1000x1000.jpg | I91: https://www.tcgplayer.com/product/502000/pokemon-sv-scarlet-and-violet-151-151-booster-bundle?Language=all&page=1
A92: Sun & Moon Elite Trainer Box [Solgaleo] | B92: Sun & Moon Base Set | C92: Sun & Moon ETB [Solgaleo] | D92: Sealed | E92: 2 | F92: 1150 | H92: https://tcgplayer-cdn.tcgplayer.com/product/126089_in_1000x1000.jpg | I92: https://www.tcgplayer.com/product/126089/pokemon-sm-base-set-sun-and-moon-elite-trainer-box-solgaleo?Language=all&page=1
A93: Mega Evolution Pokemon Center Elite Trainer Box [Mega Lucario] | B93: Mega Evolution | C93: Mega Evolution PC ETB [Mega Lucario] | D93: Sealed | E93: 2 | F93: 1140 | H93: https://tcgplayer-cdn.tcgplayer.com/product/644282_in_1000x1000.jpg | I93: https://www.tcgplayer.com/product/644282/pokemon-me01-mega-evolution-mega-evolution-pokemon-center-elite-trainer-box-exclusive-mega-lucario?Language=all&page=1
A94: Hidden Fates Pin Collection [Mew] | B94: Hidden Fates | C94: Hidden Fates Pin Collection [Mew] | D94: Sealed | E94: 2 | F94: 1130 | H94: https://tcgplayer-cdn.tcgplayer.com/product/193439_in_1000x1000.jpg | I94: https://www.tcgplayer.com/product/193439/pokemon-hidden-fates-hidden-fates-pin-collection-mew?Language=all&page=1
A95: Prismatic Evolutions Lucario ex & Tyranitar ex Premium Collection (Sam's Club) | B95: Prismatic Evolutions | C95: Prismatic Evolutions Lucario ex & Tyranitar ex Premium Collection (Sam's Club) | D95: Sealed | E95: 2 | F95: 1120 | H95: https://tcgplayer-cdn.tcgplayer.com/product/648365_in_1000x1000.jpg | I95: https://www.tcgplayer.com/product/648365/pokemon-miscellaneous-cards-and-products-prismatic-evolutions-lucario-ex-and-tyranitar-ex-premium-collection-sams-club?Language=all&page=1
A96: Paldean Fates Premium Collection [Skeledirge ex] | B96: Paldean Fates | C96: Paldean Fates Premium Collection [Skeledirge ex] | D96: Sealed | E96: 2 | F96: 1110 | H96: https://tcgplayer-cdn.tcgplayer.com/product/528080_in_1000x1000.jpg | I96: https://www.tcgplayer.com/product/528080/pokemon-sv-paldean-fates-paldean-fates-premium-collection-skeledirge-ex?Language=all&page=1
A97: Hidden Fates Collection [Charizard GX] | B97: Hidden Fates | C97: Hidden Fates Collection [Charizard GX] | D97: Sealed | E97: 2 | F97: 1100 | H97: https://tcgplayer-cdn.tcgplayer.com/product/205159_in_1000x1000.jpg | I97: https://www.tcgplayer.com/product/205159/pokemon-hidden-fates-hidden-fates-collection-charizard-gx?Language=all&page=1
A98: Hidden Fates Collection [Raichu GX] | B98: Hidden Fates | C98: Hidden Fates Collection [Raichu GX] | D98: Sealed | E98: 2 | F98: 1090 | H98: https://tcgplayer-cdn.tcgplayer.com/product/205161_in_1000x1000.jpg | I98: https://www.tcgplayer.com/product/205161/pokemon-hidden-fates-hidden-fates-collection-raichu-gx?Language=all&page=1
A99: Mega Evolution Pokemon Center Elite Trainer Box [Mega Gardevoir] | B99: Mega Evolution | C99: Mega Evolution PC ETB [Mega Gardevoir] | D99: Sealed | E99: 2 | F99: 1080 | H99: https://tcgplayer-cdn.tcgplayer.com/product/648415_in_1000x1000.jpg | I99: https://www.tcgplayer.com/product/648415/pokemon-me01-mega-evolution-mega-evolution-pokemon-center-elite-trainer-box-exclusive-mega-gardevoir?Language=all&page=1
A100: Hidden Fates Pin Collection [Mewtwo] | B100: Hidden Fates | C100: Hidden Fates Pin Collection [Mewtwo] | D100: Sealed | E100: 2 | F100: 1070 | H100: https://tcgplayer-cdn.tcgplayer.com/product/193440_in_1000x1000.jpg | I100: https://www.tcgplayer.com/product/193440/pokemon-hidden-fates-hidden-fates-pin-collection-mewtwo?Language=all&page=1
A101: Astral Radiance Pokemon Center Elite Trainer Box | B101: Astral Radiance | C101: Astral Radiance PC ETB | D101: Sealed | E101: 2 | F101: 1060 | H101: https://tcgplayer-cdn.tcgplayer.com/product/265528_in_1000x1000.jpg | I101: https://www.tcgplayer.com/product/265528/pokemon-swsh10-astral-radiance-astral-radiance-pokemon-center-elite-trainer-box-exclusive?Language=all&page=1
A102: Twilight Masquerade Pokemon Center Elite Trainer Box | B102: Twilight Masquerade | C102: Twilight Masquerade PC ETB | D102: Sealed | E102: 2 | F102: 1050 | H102: https://tcgplayer-cdn.tcgplayer.com/product/543844_in_1000x1000.jpg | I102: https://www.tcgplayer.com/product/543844/pokemon-sv06-twilight-masquerade-twilight-masquerade-pokemon-center-elite-trainer-box-exclusive?Language=all&page=1
A103: Hidden Fates Collection [Gyarados GX] | B103: Hidden Fates | C103: Hidden Fates Collection [Gyarados GX] | D103: Sealed | E103: 2 | F103: 1040 | H103: https://tcgplayer-cdn.tcgplayer.com/product/205160_in_1000x1000.jpg | I103: https://www.tcgplayer.com/product/205160/pokemon-hidden-fates-hidden-fates-collection-gyarados-gx?Language=all&page=1
... A119: Celebrations Collection [Dark Sylveon V] | B119: Celebrations | C119: Celebrations Collection [Dark Sylveon V] | D119: Sealed | E119: 2 | F119: 880 | H119: https://tcgplayer-cdn.tcgplayer.com/product/242809_in_1000x1000.jpg | I119: https://www.tcgplayer.com/product/242809/pokemon-celebrations-celebrations-collection-dark-sylveon-v?Language=all&page=1
A120: 151: Alakazam ex Collection | B120: 151 | C120: 151: Alakazam ex Collection | D120: Sealed | E120: 2 | F120: 870 | H120: https://tcgplayer-cdn.tcgplayer.com/product/502006_in_1000x1000.jpg | I120: https://www.tcgplayer.com/product/502006/pokemon-sv-scarlet-and-violet-151-151-alakazam-ex-collection?Language=all&page=1
A121: Phantasmal Flames Elite Trainer Box | B121: Phantasmal Flames | C121: Phantasmal Flames ETB | D121: Sealed | E121: 2 | F121: 860 | H121: https://tcgplayer-cdn.tcgplayer.com/product/654136_in_1000x1000.jpg | I121: https://www.tcgplayer.com/product/654136/pokemon-me02-phantasmal-flames-phantasmal-flames-elite-trainer-box?Language=all&page=1
A122: Morpeko V-UNION Playmat Premium Collection | B122: Crown Zenith | C122: Morpeko VPlaymat Premium Collection | D122: Sealed | E122: 2 | F122: 850 | H122: https://tcgplayer-cdn.tcgplayer.com/product/475644_in_1000x1000.jpg | I122: https://www.tcgplayer.com/product/475644/pokemon-crown-zenith-morpeko-v-union-playmat-premium-collection?Language=all&page=1
A123: Black Bolt Elite Trainer Box | B123: Black Bolt | C123: Black Bolt ETB | D123: Sealed | E123: 2 | F123: 840 | H123: https://tcgplayer-cdn.tcgplayer.com/product/630686_in_1000x1000.jpg | I123: https://www.tcgplayer.com/product/630686/pokemon-sv-black-bolt-black-bolt-elite-trainer-box?Language=all&page=1
A124: Shrouded Fable Elite Trainer Box | B124: Shrouded Fable | C124: Shrouded Fable ETB | D124: Sealed | E124: 2 | F124: 830 | H124: https://tcgplayer-cdn.tcgplayer.com/product/552999_in_1000x1000.jpg | I124: https://www.tcgplayer.com/product/552999/pokemon-sv-shrouded-fable-shrouded-fable-elite-trainer-box?page=1&Language=English
...

Sheet Purchase History
A1: PURCHASE HISTORY — Manual entry of all items bought (for P&L cost basis)
A2: Add a row for every purchase. Use the same short_name as the Inventory tab. The P&L tab uses FIFO order (earliest date first) to calculate cost of goods sold.
A3: date | B3: short_name | C3: product_name | D3: quantity | E3: unit_cost | F3: total_cost | G3: notes
A4: Date purchased (MM/DD/YY) | B4: Must match Inventory short_name exactly | C4: Full name (reference only) | D4: Units purchased | E4: Price paid per unit ($) | F4: =D*E (auto) -> #NAME? | G4: Seller, event, condition notes
A5: 01/01/26 | B5: 151 ETB | C5: Scarlet & Violet 151 Elite Trainer Box | D5: 4 | E5: 68 | F5: =D5*E5 -> 272 | G5: Initial stock
A6: 01/01/26 | B6: Evolving Skies Box | C6: Evolving Skies Booster Box | D6: 2 | E6: 200 | F6: =D6*E6 -> 400 | G6: Initial stock
A7: 01/01/26 | B7: Zard 151 SIR | C7: Charizard ex 199/165 SIR | D7: 1 | E7: 144 | F7: =D7*E7 -> 144 | G7: Initial stock NM
A8: 01/01/26 | B8: Pikachu Grey Hat PSA 9 | C8: 2023 Pokemon Van Gogh Pikachu Grey Felt Hat #085 | D8: 1 | E8: 256 | F8: =D8*E8 -> 256 | G8: Initial stock
A9: 01/01/26 | B9: Psyduck Munch PSA 8 | C9: 2018 Pokemon Japanese Psyduck Munch #286SMP | D9: 1 | E9: 76 | F9: =D9*E9 -> 76 | G9: Initial stock
F10: =D10*E10 -> 0
F11: =D11*E11 -> 0
F12: =D12*E12 -> 0
F13: =D13*E13 -> 0
F14: =D14*E14 -> 0
F15: =D15*E15 -> 0
F16: =D16*E16 -> 0
F17: =D17*E17 -> 0
F18: =D18*E18 -> 0
F19: =D19*E19 -> 0
F20: =D20*E20 -> 0
F21: =D21*E21 -> 0
... F34: =D34*E34 -> 0

Sheet P&L
A1: P&L STATEMENT — FIFO Cost Basis (paste Sales Log data below, then update formulas)
A2: Paste your Sales Log export here (columns A-K match the Sales CSV export). Column L calculates FIFO profit using Purchase History. Update the VLOOKUP range as you add purchase data.
A3: HOW TO USE: Export Sales CSV from app → paste starting at row 5 → Column L auto-calculates profit per line item using FIFO avg cost from Purchase History
A4: Transaction # | B4: Date | C4: Time | D4: Item | E4: Qty | F4: Unit Price | G4: Item Discount | H4: Line Total | I4: Cart Discount | J4: Grand Total | K4: Payment | L4: Profit / Loss
A5: Sale ID | B5: Sale date | C5: Sale time | D5: Product sold | E5: Units sold | F5: Sell price each | G5: Per-item disc | H5: Net line revenue | I5: Cart-level disc | J5: Transaction total | K5: Method | L5: FIFO profit (auto)
A6: 032626-001 | B6: 03/26/26 | C6: 10:30 AM | D6: Evolving Skies Box | E6: 1 | F6: 250 | H6: 250 | J6: 250 | K6: Cash | L6: =H6-(E6*IFERROR(AVERAGEIF('Purchase History'!B:B,D6,'Purchase History'!E:E),0)) -> 50
A7: 032626-001 | B7: 03/26/26 | C7: 10:30 AM | D7: 151 ETB | E7: 2 | F7: 85 | H7: 170 | L7: =H7-(E7*IFERROR(AVERAGEIF('Purchase History'!B:B,D7,'Purchase History'!E:E),0)) -> 34
A8: 032626-001 | B8: 03/26/26 | C8: 10:30 AM | D8: [2 items] | I8: 20 | J8: 400
L9: =IF(E9<>"",H9-(E9*IFERROR(AVERAGEIF('Purchase History'!B:B,D9,'Purchase History'!E:E),0)),"")
L10: =IF(E10<>"",H10-(E10*IFERROR(AVERAGEIF('Purchase History'!B:B,D10,'Purchase History'!E:E),0)),"")
L11: =IF(E11<>"",H11-(E11*IFERROR(AVERAGEIF('Purchase History'!B:B,D11,'Purchase History'!E:E),0)),"")
L12: =IF(E12<>"",H12-(E12*IFERROR(AVERAGEIF('Purchase History'!B:B,D12,'Purchase History'!E:E),0)),"")
L13: =IF(E13<>"",H13-(E13*IFERROR(AVERAGEIF('Purchase History'!B:B,D13,'Purchase History'!E:E),0)),"")
L14: =IF(E14<>"",H14-(E14*IFERROR(AVERAGEIF('Purchase History'!B:B,D14,'Purchase History'!E:E),0)),"")
L15: =IF(E15<>"",H15-(E15*IFERROR(AVERAGEIF('Purchase History'!B:B,D15,'Purchase History'!E:E),0)),"")
L16: =IF(E16<>"",H16-(E16*IFERROR(AVERAGEIF('Purchase History'!B:B,D16,'Purchase History'!E:E),0)),"")
L17: =IF(E17<>"",H17-(E17*IFERROR(AVERAGEIF('Purchase History'!B:B,D17,'Purchase History'!E:E),0)),"")
L18: =IF(E18<>"",H18-(E18*IFERROR(AVERAGEIF('Purchase History'!B:B,D18,'Purchase History'!E:E),0)),"")
L19: =IF(E19<>"",H19-(E19*IFERROR(AVERAGEIF('Purchase History'!B:B,D19,'Purchase History'!E:E),0)),"")
L20: =IF(E20<>"",H20-(E20*IFERROR(AVERAGEIF('Purchase History'!B:B,D20,'Purchase History'!E:E),0)),"")
... L38: =IF(E38<>"",H38-(E38*IFERROR(AVERAGEIF('Purchase History'!B:B,D38,'Purchase History'!E:E),0)),"")
A40: SUMMARY
A41: Total Revenue | B41: =SUMIF(E6:E38,">0",H6:H38) -> 0
A42: Total Discounts | B42: =SUMIF(G6:G38,">0",G6:G38)+SUMIF(I6:I38,">0",I6:I38) -> 0
A43: Total Cost (FIFO avg) | B43: =SUMPRODUCT((E6:E38>0)*(E6:E38)*IFERROR(AVERAGEIF('Purchase History'!B:B,D6:D38,'Purchase History'!E:E),0)) -> 0
A44: Gross Profit | B44: =B41-B42-B43 -> 0

Sheet Sales Log
A1: SALES LOG — App syncs here via End Show
A2: Transaction # | B2: Date | C2: Time | D2: Item | E2: Qty | F2: Unit Price | G2: Item Discount | H2: Line Total | I2: Cart Discount | J2: Grand Total | K2: Payment Method(s)
A3: App syncs here via End Show / End Day button. Also paste CSV exports here.

Sheet Buy-Trade Log
A1: BUY/TRADE LOG — App syncs here via End Show
A2: Type | B2: Date | C2: Time | D2: Item | E2: Qty | F2: Value | G2: Price Paid | H2: Notes | I2: Total | J2: Credit Given | K2: Balance Due | L2: Payment | M2: Transaction ID
A3: App syncs here via End Show / End Day button.

Sheet Inventory Snapshot
A1: INVENTORY SNAPSHOT — App pushes end-of-show stock levels here
A2: Snapshot Date | B2: Short Name | C2: Product Name | D2: Set | E2: Type | F2: Qty | G2: Sticker Price | H2: Notes
A3: Each End Show push appends a new snapshot. Keep historic rows to track stock over time.

Sheet Instructions
A1: KITCHEN TCG WORKBOOK GUIDE
A3: SHEET: Inventory | B3: Master source. Fill in your products. avg_purchase_price is calculated automatically from Purchase History — do not edit that column manually. Publish this tab as CSV and sync to the app via Setup → Google Sheets Sync.
A4: SHEET: Purchase History | B4: Manual entry of every item you have bought. Use the same short_name as the Inventory tab. Add a row each time you acquire stock. The P&L tab uses AVERAGEIF across all rows to calculate your average cost per item (approximation of FIFO — for true FIFO use the formula guidance below).
A5: SHEET: P&L | B5: Paste your Sales Log CSV exports here. Column L auto-calculates profit per line using your average purchase cost from Purchase History. Summary section at row 40 shows totals.
A6: P&L Formula (FIFO approx) | B6: The formula =H-((E)*AVERAGEIF('Purchase History'!B:B,D,'Purchase History'!E:E)) gives average cost across all purchases of that item. For strict FIFO, you would track the earliest unallocated purchase cost manually.
A7: SHEET: Sales Log | B7: Populated by app via End Show → Sync. Also paste Sales CSV exports here.
A8: SHEET: Buy-Trade Log | B8: Populated by app via End Show → Sync. Also paste Buy/Trade CSV exports.
A9: SHEET: Inventory Snapshot | B9: Populated by app via End Show → Sync. Each sync appends a new dated snapshot. Keep all rows to track stock over time.
A11: APP: End Show / End Day | B11: In the app: ⚙ Setup → End Show / End Day. Syncs all data to Sheets then clears logs. If sync fails, logs are NOT cleared. You can also clear without syncing as a fallback.
A12: APP: Export CSV | B12: In the app: ⚙ Setup → Export Data section. Downloads Sales, Inventory, and Buy/Trade as separate CSV files without clearing anything.
A13: APP: Sync Inventory from Sheet | B13: Reads your Inventory tab and loads all products + sticker prices into the app. Replaces current inventory.
A14: short_name MATCHING | B14: Purchase History short_name must exactly match Inventory short_name for P&L formulas to work correctly. Case-insensitive in the app but exact in Excel/Sheets formulas.
A15: avg_purchase_price column | B15: This column in Inventory uses: =IFERROR(AVERAGEIF('Purchase History'!B:B,C2,'Purchase History'!E:E),"No purchase data"). Replace C2 with the short_name cell for each row. Copy down as you add items.
A16: SEED DATA NOTE | B16: Purchase History is pre-populated with 1/1/26 entries at 80% of your sticker price as a starting cost basis. Update these with your actual purchase prices as you know them.
